google/cloud/commerce_consumer_procurement/__init__.py
google/cloud/commerce_consumer_procurement/gapic_version.py
google/cloud/commerce_consumer_procurement/py.typed
google/cloud/commerce_consumer_procurement_v1/__init__.py
google/cloud/commerce_consumer_procurement_v1/gapic_metadata.json
google/cloud/commerce_consumer_procurement_v1/gapic_version.py
google/cloud/commerce_consumer_procurement_v1/py.typed
google/cloud/commerce_consumer_procurement_v1/services/__init__.py
google/cloud/commerce_consumer_procurement_v1/services/consumer_procurement_service/__init__.py
google/cloud/commerce_consumer_procurement_v1/services/consumer_procurement_service/async_client.py
google/cloud/commerce_consumer_procurement_v1/services/consumer_procurement_service/client.py
google/cloud/commerce_consumer_procurement_v1/services/consumer_procurement_service/pagers.py
google/cloud/commerce_consumer_procurement_v1/services/consumer_procurement_service/transports/__init__.py
google/cloud/commerce_consumer_procurement_v1/services/consumer_procurement_service/transports/base.py
google/cloud/commerce_consumer_procurement_v1/services/consumer_procurement_service/transports/grpc.py
google/cloud/commerce_consumer_procurement_v1/services/consumer_procurement_service/transports/grpc_asyncio.py
google/cloud/commerce_consumer_procurement_v1/services/consumer_procurement_service/transports/rest.py
google/cloud/commerce_consumer_procurement_v1/services/consumer_procurement_service/transports/rest_base.py
google/cloud/commerce_consumer_procurement_v1/services/license_management_service/__init__.py
google/cloud/commerce_consumer_procurement_v1/services/license_management_service/async_client.py
google/cloud/commerce_consumer_procurement_v1/services/license_management_service/client.py
google/cloud/commerce_consumer_procurement_v1/services/license_management_service/pagers.py
google/cloud/commerce_consumer_procurement_v1/services/license_management_service/transports/__init__.py
google_cloud_commerce_consumer_procurement-0.4.0.dist-info/licenses/LICENSE
google_cloud_commerce_consumer_procurement-0.4.0.dist-info/METADATA
google_cloud_commerce_consumer_procurement-0.4.0.dist-info/WHEEL
google_cloud_commerce_consumer_procurement-0.4.0.dist-info/top_level.txt
google_cloud_commerce_consumer_procurement-0.4.0.dist-info/RECORD
